t_fujita/__init__.py
t_fujita/card.py
t_fujita-2.0.1.dist-info/METADATA
t_fujita-2.0.1.dist-info/WHEEL
t_fujita-2.0.1.dist-info/entry_points.txt
t_fujita-2.0.1.dist-info/RECORD
