Metadata-Version: 2.3
Name: t-fujita
Version: 2.0.1
Summary: pipx run t-fujita
Author: TomoyaFujita2016
Author-email: fujita.t.2016c@gmail.com
Requires-Python: >=3.8,<4.0
Classifier: Programming Language :: Python :: 3
Classifier: Programming Language :: Python :: 3.8
Classifier: Programming Language :: Python :: 3.9
Classifier: Programming Language :: Python :: 3.10
Classifier: Programming Language :: Python :: 3.11
Classifier: Programming Language :: Python :: 3.12
Classifier: Programming Language :: Python :: 3.13
Requires-Dist: terminaltexteffects (>=0.12.0,<0.13.0)
Requires-Dist: typer (>=0.9.0,<0.10.0)
